mezzanine_vendors-1.2.0.dist-info/DESCRIPTION.rst
mezzanine_vendors-1.2.0.dist-info/METADATA
mezzanine_vendors-1.2.0.dist-info/RECORD
mezzanine_vendors-1.2.0.dist-info/WHEEL
mezzanine_vendors-1.2.0.dist-info/metadata.json
mezzanine_vendors-1.2.0.dist-info/top_level.txt
vendors/__init__.py
vendors/admin.py
vendors/apps.py
vendors/models.py
vendors/resources.py
vendors/urls.py
vendors/views.py
vendors/management/__init__.py
vendors/management/commands/__init__.py
vendors/management/commands/add_vendor_locations.py
vendors/migrations/0001_initial.py
vendors/migrations/0002_vendor_geolocation_updated.py
vendors/migrations/__init__.py
