Metadata-Version: 2.0
Name: mezzanine-vendors
Version: 1.2.0
Summary: A vendor catalog app for Mezzanine
Home-page: https://github.com/unplugstudio/mezzanine-vendors
Author: Ed Rivas
Author-email: ed@unplug.studio
License: MIT
Keywords: django mezzanine
Platform: UNKNOWN
Classifier: Development Status :: 5 - Production/Stable
Classifier: Intended Audience :: Developers
Classifier: Topic :: Software Development :: Libraries
Classifier: License :: OSI Approved :: MIT License
Classifier: Programming Language :: Python :: 2
Classifier: Programming Language :: Python :: 2.7
Classifier: Programming Language :: Python :: 3
Classifier: Programming Language :: Python :: 3.6
Requires-Dist: django (>=1.11)
Requires-Dist: django-import-export (>=1.2)
Requires-Dist: django-google-maps (>=0.10)
Requires-Dist: googlemaps (>=3)
Requires-Dist: mezzanine (>=4.3)
Requires-Dist: mezzy (>=2.2)
